env_manager/__init__.py
env_manager/env_local.py
env_manager/env_manager.py
env_manager/environment.py
env_manager/package_manager.py
env_manager/program_state.py
env_manager/py.typed
env_manager/runners/__init__.py
env_manager/runners/irunner.py
env_manager/runners/local_runner.py
env_manager/runners/progress_runner.py
env_manager/runners/runner.py
env_manager/runners/runner_factory.py
python_env_manager-1.0.3.dist-info/LICENSE
python_env_manager-1.0.3.dist-info/METADATA
python_env_manager-1.0.3.dist-info/WHEEL
python_env_manager-1.0.3.dist-info/top_level.txt
python_env_manager-1.0.3.dist-info/RECORD
