Metadata-Version: 2.2
Name: python-env-manager
Version: 1.0.3
Summary: A comprehensive tool that streamlines the creation and management of Python virtual environments.
Author: r4d4m4n71s
License: MIT License
Project-URL: Homepage, https://github.com/r4d4m4n71s/Python-env_manager
Project-URL: Bug Tracker, https://github.com/r4d4m4n71s/Python-env_manager/issues
Project-URL: Documentation, https://github.com/r4d4m4n71s/Python-env_manager/blob/main/README.md
Classifier: Development Status :: 4 - Beta
Classifier: Intended Audience :: Developers
Classifier: Programming Language :: Python :: 3
Classifier: Programming Language :: Python :: 3.7
Classifier: Programming Language :: Python :: 3.8
Classifier: Programming Language :: Python :: 3.9
Classifier: Programming Language :: Python :: 3.10
Classifier: Programming Language :: Python :: 3.11
Classifier: Programming Language :: Python :: 3.12
Classifier: License :: OSI Approved :: MIT License
Classifier: Operating System :: OS Independent
Classifier: Topic :: Software Development :: Libraries :: Python Modules
Classifier: Topic :: Utilities
Requires-Python: >=3.7
License-File: LICENSE
Requires-Dist: rich>=10.0.0
Requires-Dist: progress-runner>=0.0.3
Provides-Extra: dev
Requires-Dist: pytest>=6.0; extra == "dev"
Requires-Dist: pytest-cov>=4.0; extra == "dev"
Requires-Dist: coverage>=7.0; extra == "dev"
Requires-Dist: black; extra == "dev"
Requires-Dist: isort; extra == "dev"
Requires-Dist: mypy; extra == "dev"
